di_ioc/__about__.py
di_ioc/__init__.py
di_ioc/abstraction.py
di_ioc/container.py
di_ioc/factory.py
di_ioc/lifetimes.py
di_ioc/scope.py
di_ioc-0.0.5.dist-info/METADATA
di_ioc-0.0.5.dist-info/WHEEL
di_ioc-0.0.5.dist-info/licenses/LICENSE.txt
di_ioc-0.0.5.dist-info/RECORD
